ipaacar/components.cpython-311-darwin.so
ipaacar/components.pyi
ipaacar/handler.py
ipaacar/legacy.py
ipaacar/py.typed
ipaacar_python-0.2.1.dist-info/METADATA
ipaacar_python-0.2.1.dist-info/WHEEL
ipaacar_python-0.2.1.dist-info/licenses/LICENSE
ipaacar_python-0.2.1.dist-info/RECORD
