Metadata-Version: 2.4
Name: ipaacar-python
Version: 0.2.1
Classifier: Programming Language :: Rust
Classifier: Programming Language :: Python :: Implementation :: CPython
Classifier: Programming Language :: Python :: Implementation :: PyPy
Classifier: Programming Language :: Python :: 3.8
Classifier: Programming Language :: Python :: 3.9
Classifier: Programming Language :: Python :: 3.10
Classifier: Programming Language :: Python :: 3.11
Classifier: Programming Language :: Python :: 3.12
Classifier: Programming Language :: Python :: 3.13
Classifier: License :: OSI Approved :: GNU General Public License v3 or later (GPLv3+)
Requires-Dist: nest-asyncio>=1.5.7
License-File: LICENSE
Summary: Incremental Processing Architecture for Artificial Conversational Agents, implemented in Rust
Keywords: ipaaca,ipaacar,rust,messaging,incremental,mqtt
Author: AG-SCS
Requires-Python: >=3.8
Project-URL: homepage, https://scs.techfak.uni-bielefeld.de
Project-URL: documentation, https://scs.pages.ub.uni-bielefeld.de/ipaacar/ipaacar-python/ipaacar.html
Project-URL: repository, https://gitlab.ub.uni-bielefeld.de/scs/ipaacar
